ptnetinspector/__init__.py
ptnetinspector/__main__.py
ptnetinspector/_version.py
ptnetinspector/main.py
ptnetinspector/scan.py
ptnetinspector/data/manuf
ptnetinspector/data/vuln_catalog.csv
ptnetinspector/entities/__init__.py
ptnetinspector/entities/default_gw.py
ptnetinspector/entities/dhcp.py
ptnetinspector/entities/eap.py
ptnetinspector/entities/igmpv1v2.py
ptnetinspector/entities/igmpv3.py
ptnetinspector/entities/llmnr.py
ptnetinspector/entities/mdns.py
ptnetinspector/entities/mldv1.py
ptnetinspector/entities/mldv2.py
ptnetinspector/entities/networks.py
ptnetinspector/entities/node.py
ptnetinspector/entities/remote_node.py
ptnetinspector/entities/router.py
ptnetinspector/entities/time.py
ptnetinspector/entities/wsdiscovery.py
ptnetinspector/output/__init__.py
ptnetinspector/output/json.py
ptnetinspector/output/non_json.py
ptnetinspector/output/tmp/IGMPv1v2.csv
ptnetinspector/output/tmp/IGMPv3.csv
ptnetinspector/output/tmp/LLMNR.csv
ptnetinspector/output/tmp/MDNS.csv
ptnetinspector/output/tmp/MLDv1.csv
ptnetinspector/output/tmp/MLDv2.csv
ptnetinspector/output/tmp/RA.csv
ptnetinspector/output/tmp/addresses.csv
ptnetinspector/output/tmp/addresses_unfiltered.csv
ptnetinspector/output/tmp/default_gw.csv
ptnetinspector/output/tmp/dhcp.csv
ptnetinspector/output/tmp/eap.csv
ptnetinspector/output/tmp/ipv4_route_table.csv
ptnetinspector/output/tmp/ipv6_route_table.csv
ptnetinspector/output/tmp/localname.csv
ptnetinspector/output/tmp/networks.csv
ptnetinspector/output/tmp/packets.csv
ptnetinspector/output/tmp/remote_node.csv
ptnetinspector/output/tmp/role_node.csv
ptnetinspector/output/tmp/routers.csv
ptnetinspector/output/tmp/start_end_mode.csv
ptnetinspector/output/tmp/time_all.csv
ptnetinspector/output/tmp/time_incoming.csv
ptnetinspector/output/tmp/time_outgoing.csv
ptnetinspector/output/tmp/vendors.csv
ptnetinspector/output/tmp/vulnerability.csv
ptnetinspector/output/tmp/wsdiscovery.csv
ptnetinspector/send/__init__.py
ptnetinspector/send/send.py
ptnetinspector-0.1.7.dist-info/licenses/LICENSE
ptnetinspector-0.1.7.dist-info/METADATA
ptnetinspector-0.1.7.dist-info/WHEEL
ptnetinspector-0.1.7.dist-info/entry_points.txt
ptnetinspector-0.1.7.dist-info/top_level.txt
ptnetinspector-0.1.7.dist-info/RECORD
