Metadata-Version: 2.4
Name: ptnetinspector
Version: 0.1.7
Summary: A reconnaissance tool for IPv6/IPv4 local network scanning with vulnerability detection
Home-page: https://www.penterep.com
Author: Penterep
Author-email: Penterep <info@penterep.com>
License: GPLv3
Project-URL: Homepage, https://www.penterep.com
Project-URL: Source, https://github.com/Penterep/ptnetinspector
Project-URL: Bug Reports, https://github.com/Penterep/ptnetinspector/issues
Keywords: network,scanner,ipv6,security,vulnerability-detection,penetration-testing
Classifier: Development Status :: 4 - Beta
Classifier: Intended Audience :: Information Technology
Classifier: Intended Audience :: System Administrators
Classifier: Topic :: Security
Classifier: Topic :: System :: Networking
Classifier: Topic :: System :: Networking :: Monitoring
Classifier: License :: OSI Approved :: GNU General Public License v3 (GPLv3)
Classifier: Programming Language :: Python :: 3
Classifier: Operating System :: POSIX :: Linux
Classifier: Environment :: Console
Requires-Python: >=3.8
License-File: LICENSE
Requires-Dist: certifi>=2024.12.14
Requires-Dist: charset-normalizer>=3.4.1
Requires-Dist: idna>=3.10
Requires-Dist: netaddr>=1.3.0
Requires-Dist: netifaces>=0.11.0
Requires-Dist: numpy>=2.2.1
Requires-Dist: pandas>=2.2.3
Requires-Dist: ptlibs>=1.0.31
Requires-Dist: python-dateutil>=2.9.0
Requires-Dist: pytz>=2024.2
Requires-Dist: requests>=2.32.3
Requires-Dist: requests-toolbelt>=1.0.0
Requires-Dist: scapy>=2.6.1
Requires-Dist: six>=1.17.0
Requires-Dist: tzdata>=2024.2
Requires-Dist: urllib3>=2.3.0
Requires-Dist: tabulate>=0.9.0
Dynamic: author
Dynamic: home-page
Dynamic: license-file
Dynamic: requires-python
